{
  "main": {
    "id": "603f4f86a26698a8",
    "type": "split",
    "children": [
      {
        "id": "693c1750fd46ed16",
        "type": "tabs",
        "children": [
          {
            "id": "14addbdc3c1fc9b2",
            "type": "leaf",
            "state": {
              "type": "markdown",
              "state": {
                "file": "Trading/2022/August/2022-08-18.md",
                "mode": "source",
                "source": true
              }
            }
          }
        ]
      },
      {
        "id": "988339fab3092e46",
        "type": "tabs",
        "children": [
          {
            "id": "049d97f883ab8e71",
            "type": "leaf",
            "state": {
              "type": "empty",
              "state": {}
            }
          }
        ]
      },
      {
        "id": "37ec20b0ca18981c",
        "type": "tabs",
        "children": [
          {
            "id": "28e890a2f64fbf47",
            "type": "leaf",
            "state": {
              "type": "empty",
              "state": {}
            }
          }
        ]
      },
      {
        "id": "6eeffa93d292b40b",
        "type": "tabs",
        "children": [
          {
            "id": "60c70d1c3e03a09c",
            "type": "leaf",
            "state": {
              "type": "empty",
              "state": {}
            }
          }
        ]
      },
      {
        "id": "28efdef3686f8395",
        "type": "tabs",
        "children": [
          {
            "id": "e469f4b9a77ea87f",
            "type": "leaf",
            "state": {
              "type": "empty",
              "state": {}
            }
          }
        ]
      },
      {
        "id": "ab24ea5a25f859a0",
        "type": "tabs",
        "children": [
          {
            "id": "c99637e954105266",
            "type": "leaf",
            "state": {
              "type": "empty",
              "state": {}
            }
          }
        ]
      },
      {
        "id": "6da49ca7282ab548",
        "type": "tabs",
        "children": [
          {
            "id": "6460e8a7c0e4fe32",
            "type": "leaf",
            "state": {
              "type": "empty",
              "state": {}
            }
          }
        ]
      },
      {
        "id": "4a742b075fb2c1a7",
        "type": "tabs",
        "children": [
          {
            "id": "4c96935b806211f8",
            "type": "leaf",
            "state": {
              "type": "empty",
              "state": {}
            }
          }
        ]
      },
      {
        "id": "6be0441c6e402409",
        "type": "tabs",
        "children": [
          {
            "id": "36c434c0d19e2665",
            "type": "leaf",
            "state": {
              "type": "empty",
              "state": {}
            }
          }
        ]
      },
      {
        "id": "80c7a470dd3b3d98",
        "type": "tabs",
        "children": [
          {
            "id": "de726de462c2c91b",
            "type": "leaf",
            "state": {
              "type": "empty",
              "state": {}
            }
          }
        ]
      },
      {
        "id": "db8197579058d3e6",
        "type": "tabs",
        "children": [
          {
            "id": "d2d18bf2d3b1442d",
            "type": "leaf",
            "state": {
              "type": "empty",
              "state": {}
            }
          }
        ]
      },
      {
        "id": "7796fe19ca5be2e0",
        "type": "tabs",
        "children": [
          {
            "id": "fc8055321755efb5",
            "type": "leaf",
            "state": {
              "type": "empty",
              "state": {}
            }
          }
        ]
      },
      {
        "id": "c02582c3c06e5696",
        "type": "tabs",
        "children": [
          {
            "id": "e92270afc3f864cc",
            "type": "leaf",
            "state": {
              "type": "empty",
              "state": {}
            }
          }
        ]
      },
      {
        "id": "98b922b76f9fe126",
        "type": "tabs",
        "children": [
          {
            "id": "b1e3ea35609e6be8",
            "type": "leaf",
            "state": {
              "type": "empty",
              "state": {}
            }
          }
        ]
      },
      {
        "id": "87eb3b5e5c86c66b",
        "type": "tabs",
        "children": [
          {
            "id": "d46ba5be4ce6c017",
            "type": "leaf",
            "state": {
              "type": "empty",
              "state": {}
            }
          }
        ]
      },
      {
        "id": "061008cca1a16b35",
        "type": "tabs",
        "children": [
          {
            "id": "4b0b534169df2bd0",
            "type": "leaf",
            "state": {
              "type": "empty",
              "state": {}
            }
          }
        ]
      },
      {
        "id": "397db378c855bcf0",
        "type": "tabs",
        "children": [
          {
            "id": "7228dcd48dc342e7",
            "type": "leaf",
            "state": {
              "type": "empty",
              "state": {}
            }
          }
        ]
      },
      {
        "id": "efa5375b47b9e97b",
        "type": "tabs",
        "children": [
          {
            "id": "73dc1504f767e063",
            "type": "leaf",
            "state": {
              "type": "empty",
              "state": {}
            }
          }
        ]
      },
      {
        "id": "2cafa1c5d061efeb",
        "type": "tabs",
        "children": [
          {
            "id": "064ed3056b1c9226",
            "type": "leaf",
            "state": {
              "type": "empty",
              "state": {}
            }
          }
        ]
      },
      {
        "id": "caa23b218c3297e7",
        "type": "tabs",
        "children": [
          {
            "id": "328d07ed5d8e5a3c",
            "type": "leaf",
            "state": {
              "type": "empty",
              "state": {}
            }
          }
        ]
      },
      {
        "id": "2b17cde93c216d2c",
        "type": "tabs",
        "children": [
          {
            "id": "f26acea432ba649b",
            "type": "leaf",
            "state": {
              "type": "empty",
              "state": {}
            }
          }
        ]
      },
      {
        "id": "aa61ec586c48b259",
        "type": "tabs",
        "children": [
          {
            "id": "253e018c08469a12",
            "type": "leaf",
            "state": {
              "type": "empty",
              "state": {}
            }
          }
        ]
      },
      {
        "id": "65ceca78105f5f72",
        "type": "tabs",
        "children": [
          {
            "id": "075218fbbb6e8fb5",
            "type": "leaf",
            "state": {
              "type": "empty",
              "state": {}
            }
          }
        ]
      },
      {
        "id": "54819ee870527b9f",
        "type": "tabs",
        "children": [
          {
            "id": "c612df9b3321de11",
            "type": "leaf",
            "state": {
              "type": "empty",
              "state": {}
            }
          }
        ]
      },
      {
        "id": "0b77e6a093d861b9",
        "type": "tabs",
        "children": [
          {
            "id": "9ac2b038fad16e8d",
            "type": "leaf",
            "state": {
              "type": "empty",
              "state": {}
            }
          }
        ]
      },
      {
        "id": "dcf4347efe20f72e",
        "type": "tabs",
        "children": [
          {
            "id": "36179c2434aa31cf",
            "type": "leaf",
            "state": {
              "type": "empty",
              "state": {}
            }
          }
        ]
      },
      {
        "id": "a38fee4970810aef",
        "type": "tabs",
        "children": [
          {
            "id": "9b80c6734f3f422c",
            "type": "leaf",
            "state": {
              "type": "empty",
              "state": {}
            }
          }
        ]
      },
      {
        "id": "a94b5731bd043471",
        "type": "tabs",
        "children": [
          {
            "id": "9a488b81353c9b4a",
            "type": "leaf",
            "state": {
              "type": "empty",
              "state": {}
            }
          }
        ]
      },
      {
        "id": "aa86307999469d08",
        "type": "tabs",
        "children": [
          {
            "id": "b031ca2523d506bf",
            "type": "leaf",
            "state": {
              "type": "empty",
              "state": {}
            }
          }
        ]
      },
      {
        "id": "ed1da7f2f737dbc8",
        "type": "tabs",
        "children": [
          {
            "id": "955793e0440894e2",
            "type": "leaf",
            "state": {
              "type": "empty",
              "state": {}
            }
          }
        ]
      },
      {
        "id": "40da1a3d6a4573a8",
        "type": "tabs",
        "children": [
          {
            "id": "b987444c604bc7ad",
            "type": "leaf",
            "state": {
              "type": "empty",
              "state": {}
            }
          }
        ]
      },
      {
        "id": "d282ff1330a04818",
        "type": "tabs",
        "children": [
          {
            "id": "2ec698908790be07",
            "type": "leaf",
            "state": {
              "type": "empty",
              "state": {}
            }
          }
        ]
      },
      {
        "id": "bb46ca0ddedd633e",
        "type": "tabs",
        "children": [
          {
            "id": "55d28954db530cc6",
            "type": "leaf",
            "state": {
              "type": "empty",
              "state": {}
            }
          }
        ]
      },
      {
        "id": "49b431a338144c52",
        "type": "tabs",
        "children": [
          {
            "id": "c99da3f1856222b3",
            "type": "leaf",
            "state": {
              "type": "empty",
              "state": {}
            }
          }
        ]
      },
      {
        "id": "a215f246d37c096b",
        "type": "tabs",
        "children": [
          {
            "id": "61c9b60308b1232a",
            "type": "leaf",
            "state": {
              "type": "empty",
              "state": {}
            }
          }
        ]
      },
      {
        "id": "badf3ce2cfc06dec",
        "type": "tabs",
        "children": [
          {
            "id": "fe7ded31bcf324f3",
            "type": "leaf",
            "state": {
              "type": "empty",
              "state": {}
            }
          }
        ]
      },
      {
        "id": "cb08e868773093f5",
        "type": "tabs",
        "children": [
          {
            "id": "a62238edb986b257",
            "type": "leaf",
            "state": {
              "type": "empty",
              "state": {}
            }
          }
        ]
      },
      {
        "id": "ad969c9db7d47ede",
        "type": "tabs",
        "children": [
          {
            "id": "427236ee752907c1",
            "type": "leaf",
            "state": {
              "type": "empty",
              "state": {}
            }
          }
        ]
      },
      {
        "id": "cca6ef700d8a0312",
        "type": "tabs",
        "children": [
          {
            "id": "3f5f51c9b62c1606",
            "type": "leaf",
            "state": {
              "type": "empty",
              "state": {}
            }
          }
        ]
      },
      {
        "id": "aaf1e64d3daf1639",
        "type": "tabs",
        "children": [
          {
            "id": "defca0067d2a1830",
            "type": "leaf",
            "state": {
              "type": "empty",
              "state": {}
            }
          }
        ]
      },
      {
        "id": "1c72f954795a2f71",
        "type": "tabs",
        "children": [
          {
            "id": "e439002262ab650d",
            "type": "leaf",
            "state": {
              "type": "empty",
              "state": {}
            }
          }
        ]
      },
      {
        "id": "889a130c4cfd3806",
        "type": "tabs",
        "children": [
          {
            "id": "9408b672c9d1a29f",
            "type": "leaf",
            "state": {
              "type": "empty",
              "state": {}
            }
          }
        ]
      },
      {
        "id": "ff7ce7770f252e24",
        "type": "tabs",
        "children": [
          {
            "id": "21d00415f9103043",
            "type": "leaf",
            "state": {
              "type": "empty",
              "state": {}
            }
          }
        ]
      },
      {
        "id": "ef8d88e6e0f019c5",
        "type": "tabs",
        "children": [
          {
            "id": "a60209e1d3bc4368",
            "type": "leaf",
            "state": {
              "type": "empty",
              "state": {}
            }
          }
        ]
      },
      {
        "id": "802ef9305eb4f8ec",
        "type": "tabs",
        "children": [
          {
            "id": "4f018609edf33fab",
            "type": "leaf",
            "state": {
              "type": "empty",
              "state": {}
            }
          }
        ]
      },
      {
        "id": "1be06a73a691a118",
        "type": "tabs",
        "children": [
          {
            "id": "c3385b0f2d5edaa1",
            "type": "leaf",
            "state": {
              "type": "empty",
              "state": {}
            }
          }
        ]
      },
      {
        "id": "917fe4eb9c80e89e",
        "type": "tabs",
        "children": [
          {
            "id": "5a25602d8841b251",
            "type": "leaf",
            "state": {
              "type": "empty",
              "state": {}
            }
          }
        ]
      },
      {
        "id": "4b1c33d05c6ba9ae",
        "type": "tabs",
        "children": [
          {
            "id": "ef785601c1e5fb64",
            "type": "leaf",
            "state": {
              "type": "empty",
              "state": {}
            }
          }
        ]
      },
      {
        "id": "b958fd754c5d1182",
        "type": "tabs",
        "children": [
          {
            "id": "4e0ab2014b13b960",
            "type": "leaf",
            "state": {
              "type": "empty",
              "state": {}
            }
          }
        ]
      },
      {
        "id": "a33a875a70721207",
        "type": "tabs",
        "children": [
          {
            "id": "d5b6a2621f718c39",
            "type": "leaf",
            "state": {
              "type": "empty",
              "state": {}
            }
          }
        ]
      },
      {
        "id": "0183bcbb3bca8a60",
        "type": "tabs",
        "children": [
          {
            "id": "064123f3688578a1",
            "type": "leaf",
            "state": {
              "type": "empty",
              "state": {}
            }
          }
        ]
      },
      {
        "id": "6e58915d7d4711ec",
        "type": "tabs",
        "children": [
          {
            "id": "8e389a9b1c29402b",
            "type": "leaf",
            "state": {
              "type": "empty",
              "state": {}
            }
          }
        ]
      },
      {
        "id": "50c298fd9ab786c8",
        "type": "tabs",
        "children": [
          {
            "id": "c878c94b96acb243",
            "type": "leaf",
            "state": {
              "type": "empty",
              "state": {}
            }
          }
        ]
      },
      {
        "id": "a1ddce4b623291e5",
        "type": "tabs",
        "children": [
          {
            "id": "8131be56b5cb7ade",
            "type": "leaf",
            "state": {
              "type": "empty",
              "state": {}
            }
          }
        ]
      },
      {
        "id": "16d3c70a46a29eec",
        "type": "tabs",
        "children": [
          {
            "id": "920c614b8a1ead7a",
            "type": "leaf",
            "state": {
              "type": "empty",
              "state": {}
            }
          }
        ]
      },
      {
        "id": "75a64444159d479f",
        "type": "tabs",
        "children": [
          {
            "id": "c279050db017b4d3",
            "type": "leaf",
            "state": {
              "type": "empty",
              "state": {}
            }
          }
        ]
      },
      {
        "id": "4d4677310df65006",
        "type": "tabs",
        "children": [
          {
            "id": "c6fbdefdab4e8de4",
            "type": "leaf",
            "state": {
              "type": "empty",
              "state": {}
            }
          }
        ]
      },
      {
        "id": "27e69b5858a306d9",
        "type": "tabs",
        "children": [
          {
            "id": "070b87050b0e6c5c",
            "type": "leaf",
            "state": {
              "type": "empty",
              "state": {}
            }
          }
        ]
      },
      {
        "id": "3ea64c7466141767",
        "type": "tabs",
        "children": [
          {
            "id": "3b7bdeaebbc68c5b",
            "type": "leaf",
            "state": {
              "type": "empty",
              "state": {}
            }
          }
        ]
      },
      {
        "id": "1445b8ea1874382b",
        "type": "tabs",
        "children": [
          {
            "id": "81a3b539dd0bd440",
            "type": "leaf",
            "state": {
              "type": "empty",
              "state": {}
            }
          }
        ]
      },
      {
        "id": "7330b14892ea6c7e",
        "type": "tabs",
        "children": [
          {
            "id": "639dd0eedaf79b42",
            "type": "leaf",
            "state": {
              "type": "empty",
              "state": {}
            }
          }
        ]
      },
      {
        "id": "1ee9a4f60b31788c",
        "type": "tabs",
        "children": [
          {
            "id": "c189120fc8118828",
            "type": "leaf",
            "state": {
              "type": "empty",
              "state": {}
            }
          }
        ]
      },
      {
        "id": "9e9365fc0ab6c1db",
        "type": "tabs",
        "children": [
          {
            "id": "cfe698a27dfb620e",
            "type": "leaf",
            "state": {
              "type": "empty",
              "state": {}
            }
          }
        ]
      },
      {
        "id": "0e74fb0c1d6edf2a",
        "type": "tabs",
        "children": [
          {
            "id": "b7c0ac859a45f84d",
            "type": "leaf",
            "state": {
              "type": "empty",
              "state": {}
            }
          }
        ]
      },
      {
        "id": "c0e615ec5f27f4e0",
        "type": "tabs",
        "children": [
          {
            "id": "8c6cbef71aa751fe",
            "type": "leaf",
            "state": {
              "type": "empty",
              "state": {}
            }
          }
        ]
      },
      {
        "id": "df1246b2df58b34e",
        "type": "tabs",
        "children": [
          {
            "id": "f4cada7e7774a5c3",
            "type": "leaf",
            "state": {
              "type": "empty",
              "state": {}
            }
          }
        ]
      },
      {
        "id": "2b23adbb0662e1b9",
        "type": "tabs",
        "children": [
          {
            "id": "951bdfe76e96fcac",
            "type": "leaf",
            "state": {
              "type": "empty",
              "state": {}
            }
          }
        ]
      }
    ],
    "direction": "vertical"
  },
  "left": {
    "id": "53f7ba147d28ee3d",
    "type": "split",
    "children": [
      {
        "id": "6726c15316c37ef0",
        "type": "tabs",
        "children": [
          {
            "id": "3d3826639a97012d",
            "type": "leaf",
            "state": {
              "type": "file-explorer",
              "state": {
                "sortOrder": "byModifiedTimeReverse"
              }
            }
          },
          {
            "id": "59b1f94eae3b312e",
            "type": "leaf",
            "state": {
              "type": "search",
              "state": {
                "query": "",
                "matchingCase": false,
                "explainSearch": false,
                "collapseAll": false,
                "extraContext": false,
                "sortOrder": "alphabetical"
              }
            }
          },
          {
            "id": "84e508f9d9511077",
            "type": "leaf",
            "state": {
              "type": "starred",
              "state": {}
            }
          }
        ]
      }
    ],
    "direction": "horizontal",
    "width": 300
  },
  "right": {
    "id": "62b8be6e0af0d87f",
    "type": "split",
    "children": [
      {
        "id": "390b00738f3542a8",
        "type": "tabs",
        "children": [
          {
            "id": "77c10545a763649c",
            "type": "leaf",
            "state": {
              "type": "backlink",
              "state": {
                "collapseAll": false,
                "extraContext": false,
                "sortOrder": "alphabetical",
                "showSearch": false,
                "searchQuery": "",
                "backlinkCollapsed": false,
                "unlinkedCollapsed": true
              }
            }
          },
          {
            "id": "0b2b636b401fec2a",
            "type": "leaf",
            "state": {
              "type": "outgoing-link",
              "state": {
                "linksCollapsed": false,
                "unlinkedCollapsed": true
              }
            }
          },
          {
            "id": "6ab8c933345eba91",
            "type": "leaf",
            "state": {
              "type": "tag",
              "state": {
                "sortOrder": "frequency",
                "useHierarchy": true
              }
            }
          },
          {
            "id": "b3bb23814d866789",
            "type": "leaf",
            "state": {
              "type": "outline",
              "state": {}
            }
          }
        ]
      }
    ],
    "direction": "horizontal",
    "width": 300,
    "collapsed": true
  },
  "active": "951bdfe76e96fcac",
  "lastOpenFiles": [
    "conflict-files-obsidian-git.md",
    "Trading/2022/August/2022-08-18.md",
    "Trading/2022/August/2022-08-19.md",
    "Trading/2022/August/2022-08-17.md",
    "Trading/2022/August/2022-08-15.md",
    "Trading/2022/August/2022-08-04.md",
    "Untitled.md",
    "templates/YYYY-MM-DD.md",
    "Trading/2022/August/2022-08-11.md",
    "Trading/2022/August/2022-08-10.md"
  ]
}